zeno_build/__init__.py
zeno_build/cache_utils.py
zeno_build/version.py
zeno_build/evaluation/__init__.py
zeno_build/evaluation/audio_metrics/__init__.py
zeno_build/evaluation/audio_metrics/error.py
zeno_build/evaluation/code_metrics/__init__.py
zeno_build/evaluation/code_metrics/execution_accuracy.py
zeno_build/evaluation/code_metrics/execution_accuracy_utils.py
zeno_build/evaluation/text_features/__init__.py
zeno_build/evaluation/text_features/capitalization.py
zeno_build/evaluation/text_features/clustering.py
zeno_build/evaluation/text_features/exact_match.py
zeno_build/evaluation/text_features/frequency.py
zeno_build/evaluation/text_features/length.py
zeno_build/evaluation/text_features/numbers.py
zeno_build/evaluation/text_metrics/__init__.py
zeno_build/evaluation/text_metrics/critique.py
zeno_build/evaluation/text_tokenizers/__init__.py
zeno_build/evaluation/text_tokenizers/unicode.py
zeno_build/experiments/__init__.py
zeno_build/experiments/experiment_run.py
zeno_build/experiments/search_space.py
zeno_build/models/__init__.py
zeno_build/models/chat_generate.py
zeno_build/models/dataset_config.py
zeno_build/models/global_models.py
zeno_build/models/lm_config.py
zeno_build/models/text_generate.py
zeno_build/models/providers/__init__.py
zeno_build/models/providers/cohere_utils.py
zeno_build/models/providers/huggingface_utils.py
zeno_build/models/providers/litellm_utils.py
zeno_build/models/providers/openai_utils.py
zeno_build/models/providers/vllm_utils.py
zeno_build/optimizers/__init__.py
zeno_build/optimizers/base.py
zeno_build/optimizers/exhaustive.py
zeno_build/optimizers/random.py
zeno_build/optimizers/standard.py
zeno_build/optimizers/vizier.py
zeno_build/prompts/__init__.py
zeno_build/prompts/chat_prompt.py
zeno_build/prompts/prompt_utils.py
zeno_build/reporting/__init__.py
zeno_build/reporting/aggregate_results.py
zeno_build/reporting/reporting_utils.py
zeno_build/reporting/visualize.py
zeno_build-0.0.7.dist-info/METADATA
zeno_build-0.0.7.dist-info/WHEEL
zeno_build-0.0.7.dist-info/licenses/LICENSE
zeno_build-0.0.7.dist-info/RECORD
