Metadata-Version: 2.1
Name: zeno_build
Version: 0.0.7
Summary: A library for comparing multiple llm-based systems.
Author-email: Ángel Alexander Cabrera <alex.cabrera@gmail.com>, Graham Neubig <neubig@gmail.com>
License: MIT License
License-File: LICENSE
Classifier: Programming Language :: Python :: 3.9
Classifier: Programming Language :: Python :: 3.10
Classifier: Programming Language :: Python :: 3.11
Requires-Python: >=3.9
Requires-Dist: aiolimiter>=1.0.0
Requires-Dist: inspiredco>=0.0.2
Requires-Dist: openai>=0.27.0
Requires-Dist: zenoml>=0.6.1
Provides-Extra: test
Requires-Dist: black>=23.3.0; extra == 'test'
Requires-Dist: mypy>=1.2.0; extra == 'test'
Requires-Dist: pre-commit>=3.2.0; extra == 'test'
Requires-Dist: pytest>=6.0.0; extra == 'test'
